CHANGELOG.rst
LICENSE
MANIFEST.in
README.rst
gorilla.py
setup.cfg
setup.py
doc/Makefile
doc/caution.rst
doc/changelog.rst
doc/conf.py
doc/core.rst
doc/decorators.rst
doc/index.rst
doc/installation.rst
doc/license.rst
doc/out_there.rst
doc/overview.rst
doc/reference.rst
doc/tests.rst
doc/tutorial.rst
doc/utilities.rst
doc/versioning.rst
doc/_static/custom.css
doc/_templates/links.html
gorilla2.egg-info/PKG-INFO
gorilla2.egg-info/SOURCES.txt
gorilla2.egg-info/dependency_links.txt
gorilla2.egg-info/requires.txt
gorilla2.egg-info/top_level.txt
tests/__init__.py
tests/_testcase.py
tests/run.py
tests/test_core.py
tests/test_decorators.py
tests/test_utils.py
tests/core/__init__.py
tests/core/frommodule.py
tests/core/tomodule.py
tests/decorators/__init__.py
tests/decorators/frommodule.py
tests/decorators/tomodule.py
tests/utils/__init__.py
tests/utils/frommodule.py
tests/utils/tomodule.py
tests/utils/subpackage/__init__.py
tests/utils/subpackage/module1.py
tests/utils/subpackage/module2.py