Metadata-Version: 2.1
Name: gorilla2
Version: 3.4.0
Summary: Convenient approach to monkey patching
Home-page: https://github.com/christophercrouzet/gorilla
Author: Christopher Crouzet
Author-email: christopher@crouzet.pm
License: MIT
Keywords: gorilla monkey patch patching
Classifier: Development Status :: 4 - Beta
Classifier: Intended Audience :: Developers
Classifier: License :: OSI Approved :: MIT License
Classifier: Operating System :: OS Independent
Classifier: Programming Language :: Python
Classifier: Programming Language :: Python :: 2
Classifier: Programming Language :: Python :: 2.7
Classifier: Programming Language :: Python :: 3
Classifier: Programming Language :: Python :: 3.3
Classifier: Programming Language :: Python :: 3.4
Classifier: Programming Language :: Python :: 3.5
Classifier: Programming Language :: Python :: 3.6
Classifier: Topic :: Software Development :: Libraries :: Python Modules
Classifier: Topic :: Utilities
Provides-Extra: dev
Provides-Extra: docs
License-File: LICENSE
